.isort.cfg
CHANGELOG.rst
LICENSE
MANIFEST.in
README.rst
mypy.ini
precommit.py
pylddwrap_meta.py
pylint.rc
requirements-doc.txt
requirements.txt
setup.py
style.yapf
tox.ini
bin/pylddwrap
docs/Makefile
docs/source/changelog.rst
docs/source/conf.py
docs/source/index.rst
docs/source/lddwrap.rst
docs/source/readme.rst
lddwrap/__init__.py
lddwrap/main.py
lddwrap/py.typed
pylddwrap.egg-info/PKG-INFO
pylddwrap.egg-info/SOURCES.txt
pylddwrap.egg-info/dependency_links.txt
pylddwrap.egg-info/requires.txt
pylddwrap.egg-info/top_level.txt
tests/__init__.py
tests/test_ldd.py
tests/test_main.py