Metadata-Version: 2.1
Name: pylddwrap
Version: 1.2.2
Summary: Wrap ldd *nix utility to determine shared libraries required by a program.
Home-page: http://github.com/Parquery/lddwrap
Author: Selim Naji, Adam Radomski and Marko Ristin
Author-email: selim.naji@parquery.com, adam.radomski@parquery.com, marko.ristin@gmail.com
License: License :: OSI Approved :: MIT License
Keywords: ldd dependency dependencies lddwrap pylddwrap
Classifier: Development Status :: 5 - Production/Stable
Classifier: Intended Audience :: Developers
Classifier: License :: OSI Approved :: MIT License
Classifier: Programming Language :: Python :: Implementation :: CPython
Classifier: Programming Language :: Python :: Implementation :: PyPy
Classifier: Programming Language :: Python :: 3.6
Classifier: Programming Language :: Python :: 3.7
Classifier: Programming Language :: Python :: 3.8
Classifier: Programming Language :: Python :: 3.9
Requires-Python: >=3.6
Provides-Extra: dev
License-File: LICENSE
